bytecrafters/__init__.py
bytecrafters/signalprocessing.py
bytecrafters-8.3.1.dist-info/METADATA
bytecrafters-8.3.1.dist-info/WHEEL
bytecrafters-8.3.1.dist-info/licenses/LICENSE
bytecrafters-8.3.1.dist-info/RECORD
