Metadata-Version: 2.1
Name: bytecrafters
Version: 8.3.1
Summary: Miscellaneous Utilities and libraries
Author-email: Matteo Pi <thx.1138@inwind.it>
License-File: LICENSE
Classifier: Development Status :: 7 - Inactive
